{
    "$schema": "https://schema.management.azure.com/schemas/2019-04-01/deploymentTemplate.json#",
    "contentVersion": "1.0.0.0",
    "parameters": {
        "location": {
            "type": "string",
            "defaultValue": "[resourceGroup().location]",
            "metadata": {
                "description": "Location for all resources."
            }
        },
        "runtime": {
            "type": "string",
            "defaultValue": "dotnet",
            "allowedValues": [
                "node",
                "dotnet",
                "java"
            ],
            "metadata": {
                "description": "The language worker runtime to load in the function app."
            }
        },
        "appName": {
            "type": "string",
            "defaultValue": "[resourceGroup().name]",
            "metadata": {
                "description": "The name of the function app that you wish to create."
            }
        },
        "storageAccountType": {
            "type": "string",
            "defaultValue": "Standard_LRS",
            "allowedValues": [
                "Standard_LRS",
                "Standard_GRS",
                "Standard_RAGRS"
            ],
            "metadata": {
                "description": "Storage Account type"
            }
        }
    },
    "variables": {
        "functionAppName": "[parameters('appName')]",
        "hostingPlanName": "[parameters('appName')]",
        "applicationInsightsName": "[parameters('appName')]",
        "storageAccountName": "[resourceGroup().name]",
        "functionWorkerRuntime": "[parameters('runtime')]",
        "appInsightsResourceId": "[resourceId('Microsoft.Insights/components', variables('applicationInsightsName'))]",
        "storageBlobDataContributorRole": "[concat('/subscriptions/', subscription().subscriptionId, '/providers/Microsoft.Authorization/roleDefinitions/ba92f5b4-2d11-453d-a403-e96b0029c9fe')]"
    },
    "resources": [
        {
            "type": "Microsoft.Storage/storageAccounts",
            "apiVersion": "2019-06-01",
            "location": "[parameters('location')]",
            "name": "[variables('storageAccountName')]",
            "sku": {
                "name": "[parameters('storageAccountType')]"
            },
            "kind": "Storage"
        },
        {
            "type": "Microsoft.Insights/components",
            "apiVersion": "2018-05-01-preview",
            "location": "[parameters('location')]",
            "name": "[variables('applicationInsightsName')]",
            "kind": "web",
            "properties": {
                "Application_Type": "web",
                "ApplicationId": "[variables('applicationInsightsName')]"
            }
        },
        {
            "type": "Microsoft.Web/serverfarms",
            "apiVersion": "2019-08-01",
            "name": "[variables('hostingPlanName')]",
            "location": "[parameters('location')]",
            "sku": {
                "name": "EP1",
                "tier": "ElasticPremium"
            },
            "kind": "elastic",
            "properties": {
                "maximumElasticWorkerCount": 20
            }
        },
        {
            "type": "Microsoft.Web/sites",
            "apiVersion": "2019-08-01",
            "name": "[variables('functionAppName')]",
            "location": "[parameters('location')]",
            "dependsOn": [
                "[resourceId('Microsoft.Web/serverfarms', variables('hostingPlanName'))]",
                "[resourceId('Microsoft.Storage/storageAccounts', variables('storageAccountName'))]"
            ],
            "identity": {
                "type": "SystemAssigned"
            },
            "kind": "functionapp",
            "properties": {
                "serverFarmId": "[resourceId('Microsoft.Web/serverfarms', variables('hostingPlanName'))]",
                "siteConfig": {
                    "appSettings": [
                        {
                            "name": "APPINSIGHTS_INSTRUMENTATIONKEY",
                            "value": "[reference(variables('appInsightsResourceId'), '2018-05-01-preview').instrumentationKey]"
                        },
                        {
                            "name": "APPLICATIONINSIGHTS_CONNECTION_STRING",
                            "value": "[concat('InstrumentationKey=', reference(variables('appInsightsResourceId'), '2018-05-01-preview').instrumentationKey)]"
                        },
                        {
                            "name": "AzureWebJobsStorage",
                            "value": "[concat('DefaultEndpointsProtocol=https;AccountName=',variables('storageAccountName'), ';EndpointSuffix=', environment().suffixes.storage, ';AccountKey=',listkeys(resourceId('Microsoft.Storage/storageAccounts', variables('storageAccountName')), '2019-06-01').keys[0].value,';')]"
                        },
                        {
                            "name": "WEBSITE_CONTENTAZUREFILECONNECTIONSTRING",
                            "value": "[concat('DefaultEndpointsProtocol=https;AccountName=',variables('storageAccountName'), ';EndpointSuffix=', environment().suffixes.storage, ';AccountKey=',listkeys(resourceId('Microsoft.Storage/storageAccounts', variables('storageAccountName')), '2019-06-01').keys[0].value,';')]"
                        },
                        {
                            "name": "FUNCTIONS_EXTENSION_VERSION",
                            "value": "~3"
                        },
                        {
                            "name": "FUNCTIONS_WORKER_RUNTIME",
                            "value": "[variables('functionWorkerRuntime')]"
                        },
                        {
                            "name": "WEBSITE_NODE_DEFAULT_VERSION",
                            "value": "~12"
                        }
                    ]
                }
            },
            "resources": [
            ]
        },
        {
            "type": "Microsoft.Storage/storageAccounts/providers/roleAssignments",
            "apiVersion": "2018-09-01-preview",
            "name": "[concat(variables('storageAccountName'), '/Microsoft.Authorization/', guid(uniqueString(variables('storageAccountName'))))]",
            "dependsOn": [
                "[variables('storageAccountName')]"
            ],
            "properties": {
                "roleDefinitionId": "[variables('storageBlobDataContributorRole')]",
                "principalId": "[reference(resourceId('Microsoft.Web/sites', parameters('appName')), '2019-08-01', 'Full').identity.principalId]"
            }
        }
    ],
    "outputs": {
        "assignedManagedIdentity": {
            "type": "object",
            "value": "[reference(resourceId('Microsoft.Web/sites', parameters('appName')), '2019-08-01', 'Full').identity]"
        },
        "functionsAppName": {
            "type": "string",
            "value": "[variables('functionAppName')]"
        },
        "storageAccountName": {
            "type": "string",
            "value": "[variables('storageAccountName')]"
        }
    }
}
